{
  "currencies": [
    "USDJPY",
    "AUDUSD",
    "NZDUSD",
    "EURUSD",
    "USDCHF",
    "GBPUSD",
    "USDCAD",
    "EURCAD",
    "EURCHF",
    "AUDCAD"
  ],
  "accounts": [
    {
      "account_number": 1000100754,
      "riskDollars": "31.5",
      "execute": false
    },
    {
      "account_number": 1300087424,
      "riskDollars": "375",
      "execute": false
    },
    {
      "account_number": 1300099493,
      "riskDollars": "375",
      "execute": false
    },
    {
      "account_number": 66076442,
      "riskDollars": "30",
      "execute": false
    }
  ],
  "records": []
}